{
  "Sed-2": {
    "alt_name": "Sed-2 low-runoff sediment family",
    "ymax": 200,
    "xmax": 4000,
    "dxy": 5,
    "uplift_rate": 0.001,
    "H0": 5,
    "Sc": 1,
    "Hstar": 1,
    "V0": 0.008,
    "P0": 1e-08,
    "run_off": 0.5,
    "K_sed": 0.00234,
    "K_br": 0.000234,
    "F_f": 0.5,
    "phi": 0,
    "H_star": 0.1,
    "Vs": 1,
    "m_sp": 0.5,
    "n_sp": 1.0,
    "sp_crit_sed": 0.0,
    "sp_crit_br": 0.0,
    "total_slip": 500.0,
    "method": "roll",
    "total_steady_time": 300000.0,
    "dt_steady": 100.0,
    "dt_model": 100.0,
    "fluvial_freq": 100000.0,
    "fluvial_len": 15000.0
  },
  "Sed-3": {
    "alt_name": "Sed-3 active hillslope family",
    "ymax": 200,
    "xmax": 4000,
    "dxy": 5,
    "uplift_rate": 0.001,
    "H0": 5,
    "Sc": 1,
    "Hstar": 0.1,
    "V0": 0.08,
    "P0": 0.0001,
    "run_off": 1,
    "K_sed": 0.00234,
    "K_br": 0.000234,
    "F_f": 0.5,
    "phi": 0,
    "H_star": 0.1,
    "Vs": 1,
    "m_sp": 0.5,
    "n_sp": 1.0,
    "sp_crit_sed": 0.0,
    "sp_crit_br": 0.0,
    "total_slip": 500.0,
    "method": "roll",
    "total_steady_time": 300000.0,
    "dt_steady": 100.0,
    "dt_model": 100.0,
    "fluvial_freq": 100000.0,
    "fluvial_len": 15000.0
  },
  "Sed-4": {
    "alt_name": "Sed-4 high soil production family",
    "ymax": 200,
    "xmax": 4000,
    "dxy": 5,
    "uplift_rate": 0.001,
    "H0": 5,
    "Sc": 1,
    "Hstar": 0.1,
    "V0": 0.08,
    "P0": 0.001,
    "run_off": 1,
    "K_sed": 0.00234,
    "K_br": 0.000234,
    "F_f": 0.5,
    "phi": 0,
    "H_star": 0.1,
    "Vs": 1,
    "m_sp": 0.5,
    "n_sp": 1.0,
    "sp_crit_sed": 0.0,
    "sp_crit_br": 0.0,
    "total_slip": 500.0,
    "method": "roll",
    "total_steady_time": 300000.0,
    "dt_steady": 100.0,
    "dt_model": 100.0,
    "fluvial_freq": 100000.0,
    "fluvial_len": 15000.0
  },
  "Sed-5": {
    "alt_name": "Sed-5 no-fines family",
    "ymax": 200,
    "xmax": 4000,
    "dxy": 5,
    "uplift_rate": 0.001,
    "H0": 5,
    "Sc": 1,
    "Hstar": 0.1,
    "V0": 0.08,
    "P0": 0.0001,
    "run_off": 1,
    "K_sed": 0.00234,
    "K_br": 0.000234,
    "F_f": 0,
    "phi": 0,
    "H_star": 0.1,
    "Vs": 1,
    "m_sp": 0.5,
    "n_sp": 1.0,
    "sp_crit_sed": 0.0,
    "sp_crit_br": 0.0,
    "total_slip": 500.0,
    "method": "roll",
    "total_steady_time": 300000.0,
    "dt_steady": 100.0,
    "dt_model": 100.0,
    "fluvial_freq": 100000.0,
    "fluvial_len": 15000.0
  },
  "DT": {
    "alt_name": "Duvall-Tucker detachment-limited baseline",
    "ymax": 200,
    "xmax": 4000,
    "dxy": 5,
    "uplift_rate": 0.001,
    "H0": 0,
    "Sc": 1,
    "Hstar": 1,
    "V0": 0.008,
    "P0": 1e-08,
    "run_off": 1,
    "K_sed": 0.000234,
    "K_br": 0.000234,
    "F_f": 1,
    "phi": 0,
    "H_star": 1e-08,
    "Vs": 0,
    "m_sp": 0.5,
    "n_sp": 1.0,
    "sp_crit_sed": 0.0,
    "sp_crit_br": 0.0,
    "total_slip": 500.0,
    "method": "roll",
    "total_steady_time": 300000.0,
    "dt_steady": 100.0,
    "dt_model": 100.0,
    "fluvial_freq": 100000.0,
    "fluvial_len": 15000.0
  }
}
